[{"stimulus": "stim_25", "angle": 205, "index": 0, "stable": true, "ttype": "training"}, {"stimulus": "stim_23", "angle": 138, "index": 1, "stable": false, "ttype": "training"}, {"stimulus": "stim_22", "angle": 307, "index": 2, "stable": true, "ttype": "training"}, {"stimulus": "stim_24", "angle": 341, "index": 3, "stable": false, "ttype": "training"}, {"stimulus": "stim_21", "angle": 165, "index": 4, "stable": true, "ttype": "training"}, {"stimulus": "stim_26", "angle": 19, "index": 5, "stable": false, "ttype": "training"}, "finished training", {"stimulus": "stim_7", "angle": 230, "index": 0, "stable": false, "ttype": "experiment"}, {"stimulus": "stim_17", "angle": 5, "index": 1, "stable": false, "ttype": "experiment"}, {"stimulus": "stim_14", "angle": 115, "index": 2, "stable": true, "ttype": "experiment"}, {"stimulus": "stim_19", "angle": 150, "index": 3, "stable": true, "ttype": "experiment"}, {"stimulus": "stim_20", "angle": 152, "index": 4, "stable": true, "ttype": "experiment"}, {"stimulus": "stim_9", "angle": 173, "index": 5, "stable": true, "ttype": "experiment"}, {"stimulus": "stim_6", "angle": 272, "index": 6, "stable": true, "ttype": "experiment"}, {"stimulus": "stim_1", "angle": 342, "index": 7, "stable": false, "ttype": "experiment"}, {"stimulus": "stim_8", "angle": 172, "index": 8, "stable": true, "ttype": "experiment"}, {"stimulus": "stim_13", "angle": 126, "index": 9, "stable": false, "ttype": "experiment"}, {"stimulus": "stim_3", "angle": 180, "index": 10, "stable": false, "ttype": "experiment"}, {"stimulus": "stim_10", "angle": 306, "index": 11, "stable": false, "ttype": "experiment"}, {"stimulus": "stim_18", "angle": 55, "index": 12, "stable": false, "ttype": "experiment"}, {"stimulus": "stim_5", "angle": 239, "index": 13, "stable": true, "ttype": "experiment"}, {"stimulus": "stim_2", "angle": 284, "index": 14, "stable": false, "ttype": "experiment"}, {"stimulus": "stim_15", "angle": 263, "index": 15, "stable": false, "ttype": "experiment"}, {"stimulus": "stim_4", "angle": 287, "index": 16, "stable": true, "ttype": "experiment"}, {"stimulus": "stim_16", "angle": 109, "index": 17, "stable": true, "ttype": "experiment"}, {"stimulus": "stim_11", "angle": 189, "index": 18, "stable": true, "ttype": "experiment"}, {"stimulus": "stim_12", "angle": 110, "index": 19, "stable": false, "ttype": "experiment"}, "finished experiment", {"stimulus": "stim_25", "angle": 205, "index": 0, "stable": true, "ttype": "posttest"}, {"stimulus": "stim_23", "angle": 138, "index": 1, "stable": false, "ttype": "posttest"}, {"stimulus": "stim_22", "angle": 307, "index": 2, "stable": true, "ttype": "posttest"}, {"stimulus": "stim_24", "angle": 341, "index": 3, "stable": false, "ttype": "posttest"}, {"stimulus": "stim_21", "angle": 165, "index": 4, "stable": true, "ttype": "posttest"}, {"stimulus": "stim_26", "angle": 19, "index": 5, "stable": false, "ttype": "posttest"}, "finished posttest"]